fastapi_template/__init__.py
fastapi_template/__main__.py
fastapi_template/cli.py
fastapi_template/input_model.py
fastapi_template/template/cookiecutter.json
fastapi_template/template/hooks/__init__.py
fastapi_template/template/hooks/post_gen_project.py
fastapi_template/template/hooks/pre_gen_project.py
fastapi_template/template/{{cookiecutter.project_name}}/.dockerignore
fastapi_template/template/{{cookiecutter.project_name}}/.editorconfig
fastapi_template/template/{{cookiecutter.project_name}}/.env
fastapi_template/template/{{cookiecutter.project_name}}/.github/workflows/tests.yml
fastapi_template/template/{{cookiecutter.project_name}}/.gitignore
fastapi_template/template/{{cookiecutter.project_name}}/.gitlab-ci.yml
fastapi_template/template/{{cookiecutter.project_name}}/.pre-commit-config.yaml
fastapi_template/template/{{cookiecutter.project_name}}/Dockerfile
fastapi_template/template/{{cookiecutter.project_name}}/README.md
fastapi_template/template/{{cookiecutter.project_name}}/alembic.ini
fastapi_template/template/{{cookiecutter.project_name}}/conditional_files.json
fastapi_template/template/{{cookiecutter.project_name}}/deploy/docker-compose.dev.yml
fastapi_template/template/{{cookiecutter.project_name}}/deploy/docker-compose.otlp.yml
fastapi_template/template/{{cookiecutter.project_name}}/deploy/kube/app.yml
fastapi_template/template/{{cookiecutter.project_name}}/deploy/kube/db.yml
fastapi_template/template/{{cookiecutter.project_name}}/deploy/kube/namespace.yml
fastapi_template/template/{{cookiecutter.project_name}}/deploy/kube/rabbit.yml
fastapi_template/template/{{cookiecutter.project_name}}/deploy/kube/redis.yml
fastapi_template/template/{{cookiecutter.project_name}}/deploy/otel-collector-config.yml
fastapi_template/template/{{cookiecutter.project_name}}/docker-compose.yml
fastapi_template/template/{{cookiecutter.project_name}}/pyproject.toml
fastapi_template/template/{{cookiecutter.project_name}}/replaceable_files.json
fastapi_template-5.1.3.dist-info/LICENSE
fastapi_template-5.1.3.dist-info/METADATA
fastapi_template-5.1.3.dist-info/WHEEL
fastapi_template-5.1.3.dist-info/entry_points.txt
fastapi_template-5.1.3.dist-info/RECORD
