Metadata-Version: 2.3
Name: fastapi_template
Version: 5.1.3
Summary: Feature-rich robust FastAPI template
Keywords: FastAPI,Cookiecutter,Template
Author: Pavel Kirilin
Author-email: win10@list.ru
Requires-Python: >=3.9,<4.0
Classifier: Programming Language :: Python :: 3
Classifier: Programming Language :: Python :: 3.9
Classifier: Programming Language :: Python :: 3.10
Classifier: Programming Language :: Python :: 3.11
Classifier: Programming Language :: Python :: 3.12
Classifier: Programming Language :: Python :: 3.13
Requires-Dist: click (>=8.1.3,<9.0.0)
Requires-Dist: cookiecutter (>=1.7.3,<2.0.0)
Requires-Dist: pre-commit (>=2.14.0,<3.0.0)
Requires-Dist: prompt-toolkit (>=3.0.36,<4.0.0)
Requires-Dist: pydantic (>=1.10)
Requires-Dist: simple-term-menu (>=1.5.2,<2.0.0)
Requires-Dist: termcolor (>=1.1.0,<2.0.0)
Project-URL: Homepage, https://github.com/s3rius/FastAPI-template
Project-URL: Repository, https://github.com/s3rius/FastAPI-template
